duden/__init__.py
duden/__version__.py
duden/cli.py
duden/common.py
duden/display.py
duden/inflection.py
duden/locale/build.sh
duden/locale/de_DE.po
duden/locale/duden.pot
duden/locale/eo.po
duden/locale/es_ES.po
duden/page/__init__.py
duden/page/base.py
duden/page/grammar.py
duden/request.py
duden/word.py
duden-0.19.2.dist-info/LICENSE
duden-0.19.2.dist-info/METADATA
duden-0.19.2.dist-info/WHEEL
duden-0.19.2.dist-info/entry_points.txt
duden-0.19.2.dist-info/RECORD
